LICENSE
README.md
setup.py
FacileToolkit2/FacileToolkit2.py
FacileToolkit2/__init__.py
facile_toolkit2.egg-info/PKG-INFO
facile_toolkit2.egg-info/SOURCES.txt
facile_toolkit2.egg-info/dependency_links.txt
facile_toolkit2.egg-info/requires.txt
facile_toolkit2.egg-info/top_level.txt