Metadata-Version: 2.1
Name: facile-toolkit2
Version: 0.0.37
Summary: A robotframework keywords toolkit used by Facile.it
Home-page: https://www.facile.it
Author: Vincenzo Gasparo
Author-email: vincenzo.gasparo@gmail.com
License: UNKNOWN
Platform: UNKNOWN
Classifier: Programming Language :: Python :: 3
Classifier: License :: OSI Approved :: MIT License
Classifier: Operating System :: OS Independent
